ac8593_key_manager/__init__.py
ac8593_key_manager/key_manager.py
ac8593_key_manager-0.2.0.dist-info/METADATA
ac8593_key_manager-0.2.0.dist-info/WHEEL
ac8593_key_manager-0.2.0.dist-info/top_level.txt
ac8593_key_manager-0.2.0.dist-info/RECORD
