Metadata-Version: 2.1
Name: ac8593-key-manager
Version: 0.2.0
Summary: Key Manager library
Home-page: https://github.com/Aditya21196/key-manager
Author: Aditya Chawla
Author-email: ac8593@nyu.edu
License: MIT
Platform: UNKNOWN
Classifier: Intended Audience :: Developers
Classifier: License :: OSI Approved :: MIT License
Classifier: Programming Language :: Python
Classifier: Programming Language :: Python :: 3
Classifier: Programming Language :: Python :: 3.6
Classifier: Programming Language :: Python :: 3.7
Classifier: Programming Language :: Python :: 3.8
Classifier: Programming Language :: Python :: 3.9
Classifier: Operating System :: OS Independent
